xgb2sql/__init__.py
xgb2sql/core.py
xgb2sql-0.120.dist-info/LICENSE
xgb2sql-0.120.dist-info/METADATA
xgb2sql-0.120.dist-info/WHEEL
xgb2sql-0.120.dist-info/top_level.txt
xgb2sql-0.120.dist-info/RECORD
