Metadata-Version: 2.1
Name: xgb2sql
Version: 0.120
Summary: A simple library for converting the output of an XGB model to SQL.
Home-page: https://github.com/Chryzanthemum/xgb2sql
Author: Benjamin Jiang
Author-email: benjamin.jiang@well.co
License: Apache Software License 2.0
Keywords: xgb2sql,xgb sql,xgboost sql,xgboost to sql,xgb to sql
Classifier: Development Status :: 3 - Alpha
Classifier: Intended Audience :: Developers
Classifier: License :: OSI Approved :: Apache Software License
Classifier: Natural Language :: English
Classifier: Programming Language :: Python :: 3.6
Classifier: Programming Language :: Python :: 3.7
Classifier: Programming Language :: Python :: 3.8
Requires-Python: >=3.6
License-File: LICENSE
